supermarket_management/__init__.py
supermarket_management/employee/__init__.py
supermarket_management/employee/cashier.py
supermarket_management/employee/employee.py
supermarket_management/employee/stocker.py
supermarket_management/product/__init__.py
supermarket_management/product/cloth.py
supermarket_management/product/food.py
supermarket_management/product/product.py
supermarket_management_yt-0.1.dist-info/LICENSE.txt
supermarket_management_yt-0.1.dist-info/METADATA
supermarket_management_yt-0.1.dist-info/WHEEL
supermarket_management_yt-0.1.dist-info/top_level.txt
supermarket_management_yt-0.1.dist-info/RECORD
