Metadata-Version: 2.1
Name: supermarket-management-yt
Version: 0.1
Summary: supermarket management system for employee and product
Home-page: https://github.com/xintian927/data533_lab4.git
Author: Bowen Yang & Xin Tian
Author-email: tjyh111@163.com
License: MIT
Platform: UNKNOWN
